crumbly/__init__.py
crumbly-1.2.2.dist-info/LICENSE
crumbly-1.2.2.dist-info/METADATA
crumbly-1.2.2.dist-info/WHEEL
crumbly-1.2.2.dist-info/top_level.txt
crumbly-1.2.2.dist-info/RECORD
