Metadata-Version: 2.1
Name: crumbly
Version: 1.2.2
Summary: A Python library for versatile and user-friendly data storage and management.
Home-page: https://github.com/CapnSushiOfTheSea/crumbly
Author: CapnSushiOfTheSea
License: MIT
Classifier: Development Status :: 3 - Alpha
Classifier: Intended Audience :: Developers
Classifier: License :: OSI Approved :: MIT License
Classifier: Programming Language :: Python :: 3
Classifier: Programming Language :: Python :: 3.6
Classifier: Programming Language :: Python :: 3.7
Classifier: Programming Language :: Python :: 3.8
Classifier: Programming Language :: Python :: 3.9
Classifier: Topic :: Software Development :: Libraries
Classifier: Topic :: Utilities
License-File: LICENSE
